.DS_Store
ewechat/__init__.py
ewechat/address.py
ewechat/circle.py
ewechat/login.py
ewechat/receive.py
ewechat/send.py
ewechat-0.1.6.dist-info/LICENSE
ewechat-0.1.6.dist-info/METADATA
ewechat-0.1.6.dist-info/WHEEL
ewechat-0.1.6.dist-info/top_level.txt
ewechat-0.1.6.dist-info/RECORD
