Metadata-Version: 2.1
Name: ewechat
Version: 0.1.6
Summary: 微信接服务商（E管家）API python 接口
Home-page: https://github.com/winniesi/ewechat
Author: winniesi
Author-email: si.good@gmail.com
License: MIT
Platform: UNKNOWN
Classifier: License :: OSI Approved :: MIT License
Classifier: Programming Language :: Python
Classifier: Programming Language :: Python :: 3
Classifier: Programming Language :: Python :: 3.6
Classifier: Programming Language :: Python :: Implementation :: CPython
Classifier: Programming Language :: Python :: Implementation :: PyPy
Requires-Python: >=3.6.0
License-File: LICENSE
Requires-Dist: requests
